hyperdrivepy/hyperdrive_utils.py
hyperdrivepy/__init__.py
hyperdrivepy/hyperdrivepy.cpython-310-x86_64-linux-gnu.so
hyperdrivepy/utils.py
hyperdrivepy/types.py
hyperdrivepy/hyperdrive_state.py
hyperdrivepy/pypechain_types/utilities.py
hyperdrivepy/pypechain_types/IHyperdriveContract.py
hyperdrivepy/pypechain_types/__init__.py
hyperdrivepy/pypechain_types/IHyperdriveTypes.py
hyperdrivepy-1.0.4.dist-info/LICENSE
hyperdrivepy-1.0.4.dist-info/METADATA
hyperdrivepy-1.0.4.dist-info/RECORD
hyperdrivepy-1.0.4.dist-info/top_level.txt
hyperdrivepy-1.0.4.dist-info/WHEEL
