Metadata-Version: 2.1
Name: hyperdrivepy
Version: 1.0.4
Project-URL: Homepage, https://github.com/delvtech/hyperdrive-bindings
Project-URL: Issues, https://github.com/delvtech/hyperdrive-bindings/issues
Classifier: Programming Language :: Rust
Classifier: Programming Language :: Python :: Implementation :: CPython
Classifier: Programming Language :: Python :: Implementation :: PyPy
Requires-Python: >=3.8
License-File: LICENSE
